units/__init__.py
units/tests.py
python_units-0.1.3.dist-info/LICENSE
python_units-0.1.3.dist-info/METADATA
python_units-0.1.3.dist-info/WHEEL
python_units-0.1.3.dist-info/top_level.txt
python_units-0.1.3.dist-info/RECORD
