Metadata-Version: 2.1
Name: python-units
Version: 0.1.3
Summary: Python library to represent numbers with units
Home-page: https://bacculus.dev/paulkorir/python-units
Author: Paul K. Korir, PhD
Author-email: paul.korir@gmail.com
License: GNU GPL v3.0
Keywords: units
Platform: UNKNOWN
Classifier: Programming Language :: Python :: 2.7
Classifier: Programming Language :: Python :: 3
